{
  "generated_at": "2026-03-06T16:26:19.691016",
  "date": "March 06, 2026",
  "pairs": {
    "EURUSD=X": {
      "pair": "EUR/USD",
      "symbol": "EURUSD=X",
      "price": 1.1604,
      "day_chg_pct": -0.272,
      "direction": "SHORT",
      "conviction": 20,
      "quality": "\ud83d\ude10 NEUTRAL",
      "alignment": "TECH ONLY",
      "entry": 1.1604,
      "target": 1.14333,
      "stop": 1.17065,
      "rr_ratio": 1.67,
      "key_driver": "RSI oversold: 24.9 \u2014 potential bounce",
      "hold_period": "1-3 days",
      "tech": {
        "direction": "SHORT",
        "conviction": 28,
        "rsi": 24.9,
        "trend": "BELOW_MA50",
        "perf_20d": -1.479,
        "reasons": [
          "RSI oversold: 24.9 \u2014 potential bounce"
        ]
      },
      "macro": {
        "direction": "NEUTRAL",
        "conviction": 0,
        "signals": []
      },
      "price_context": {
        "ma20": 1.17911,
        "ma50": 1.17688,
        "ma200": 1.17008,
        "w52_high": 1.20236,
        "w52_low": 1.14701,
        "atr": 0.00683
      },
      "notes": "Most liquid pair. Very signal-friendly. Tight spreads.",
      "status": "ok",
      "hours_old": 0.0,
      "stale": false,
      "freshness": "\ud83d\udfe2 Fresh (0.0h)"
    },
    "JPY=X": {
      "pair": "USD/JPY",
      "symbol": "JPY=X",
      "price": 157.62,
      "day_chg_pct": 0.406,
      "direction": "NEUTRAL",
      "conviction": 15,
      "quality": "\ud83d\ude10 NEUTRAL",
      "alignment": "CONFLICTED \u26a0\ufe0f",
      "entry": 157.62,
      "target": 160.2941,
      "stop": 156.0155,
      "rr_ratio": 1.67,
      "key_driver": "Price above MA50 > MA200 (uptrend)",
      "hold_period": "3-7 days",
      "tech": {
        "direction": "LONG",
        "conviction": 53,
        "rsi": 75.0,
        "trend": "UPTREND",
        "perf_20d": 0.533,
        "reasons": [
          "Price above MA50 > MA200 (uptrend)",
          "RSI overbought: 75.0 \u2014 caution",
          "Near 52w high \u2014 breakout zone"
        ]
      },
      "macro": {
        "direction": "SHORT",
        "conviction": 76.0,
        "signals": [
          {
            "name": "Middle East Tension",
            "direction": "SHORT",
            "confidence": 100,
            "weight": 0.5
          },
          {
            "name": "Earnings Misses",
            "direction": "SHORT",
            "confidence": 75,
            "weight": 0.3
          },
          {
            "name": "Trump Tariff Negative",
            "direction": "SHORT",
            "confidence": 100,
            "weight": 0.4
          },
          {
            "name": "Oil Price Spike",
            "direction": "LONG",
            "confidence": 50,
            "weight": 0.3
          }
        ]
      },
      "price_context": {
        "ma20": 155.32585,
        "ma50": 156.07268,
        "ma200": 153.93737,
        "w52_high": 159.438,
        "w52_low": 146.217,
        "atr": 1.06964
      },
      "notes": "Strong macro correlation. Risk-off = JPY strengthens.",
      "status": "ok",
      "hours_old": 0.0,
      "stale": false,
      "freshness": "\ud83d\udfe2 Fresh (0.0h)"
    },
    "GBPUSD=X": {
      "pair": "GBP/USD",
      "symbol": "GBPUSD=X",
      "price": 1.339,
      "day_chg_pct": 0.153,
      "direction": "SHORT",
      "conviction": 20,
      "quality": "\ud83d\ude10 NEUTRAL",
      "alignment": "TECH ONLY",
      "entry": 1.339,
      "target": 1.3168,
      "stop": 1.35232,
      "rr_ratio": 1.67,
      "key_driver": "RSI oversold: 28.7 \u2014 potential bounce",
      "hold_period": "1-3 days",
      "tech": {
        "direction": "SHORT",
        "conviction": 28,
        "rsi": 28.7,
        "trend": "BELOW_MA50",
        "perf_20d": -0.968,
        "reasons": [
          "RSI oversold: 28.7 \u2014 potential bounce"
        ]
      },
      "macro": {
        "direction": "NEUTRAL",
        "conviction": 0,
        "signals": []
      },
      "price_context": {
        "ma20": 1.35238,
        "ma50": 1.35322,
        "ma200": 1.34134,
        "w52_high": 1.38468,
        "w52_low": 1.30117,
        "atr": 0.00888
      },
      "notes": "High volatility. Strong news-driven moves.",
      "status": "ok",
      "hours_old": 0.0,
      "stale": false,
      "freshness": "\ud83d\udfe2 Fresh (0.0h)"
    },
    "CAD=X": {
      "pair": "USD/CAD",
      "symbol": "CAD=X",
      "price": 1.36,
      "day_chg_pct": -0.191,
      "direction": "SHORT",
      "conviction": 21,
      "quality": "\ud83d\ude10 NEUTRAL",
      "alignment": "TECH ONLY",
      "entry": 1.36,
      "target": 1.34575,
      "stop": 1.36855,
      "rr_ratio": 1.67,
      "key_driver": "Price below MA50 < MA200 (downtrend)",
      "hold_period": "1-3 days",
      "tech": {
        "direction": "SHORT",
        "conviction": 30,
        "rsi": 49.9,
        "trend": "DOWNTREND",
        "perf_20d": -0.69,
        "reasons": [
          "Price below MA50 < MA200 (downtrend)",
          "RSI healthy: 49.9"
        ]
      },
      "macro": {
        "direction": "NEUTRAL",
        "conviction": 11.0,
        "signals": [
          {
            "name": "Middle East Tension",
            "direction": "SHORT",
            "confidence": 100,
            "weight": 0.4
          },
          {
            "name": "Trump Tariff Negative",
            "direction": "LONG",
            "confidence": 100,
            "weight": 0.6
          },
          {
            "name": "Oil Price Spike",
            "direction": "SHORT",
            "confidence": 50,
            "weight": 0.7
          }
        ]
      },
      "price_context": {
        "ma20": 1.36452,
        "ma50": 1.37089,
        "ma200": 1.38476,
        "w52_high": 1.41395,
        "w52_low": 1.3484,
        "atr": 0.0057
      },
      "notes": "Oil-correlated. Most relevant to Canadian investor.",
      "status": "ok",
      "hours_old": 0.0,
      "stale": false,
      "freshness": "\ud83d\udfe2 Fresh (0.0h)"
    },
    "GC=F": {
      "pair": "XAU/USD (Gold)",
      "symbol": "GC=F",
      "price": 5161.3,
      "day_chg_pct": 1.895,
      "direction": "LONG",
      "conviction": 76,
      "quality": "\ud83d\udd25 STRONG",
      "alignment": "ALIGNED \u2705",
      "entry": 5161.3,
      "target": 5412.47868,
      "stop": 5010.5928,
      "rr_ratio": 1.67,
      "key_driver": "Price above MA50 > MA200 (uptrend)",
      "hold_period": "3-7 days",
      "tech": {
        "direction": "LONG",
        "conviction": 60,
        "rsi": 56.4,
        "trend": "UPTREND",
        "perf_20d": 6.169,
        "reasons": [
          "Price above MA50 > MA200 (uptrend)",
          "Strong 20d momentum: +6.169%",
          "RSI healthy: 56.4"
        ]
      },
      "macro": {
        "direction": "LONG",
        "conviction": 90,
        "signals": [
          {
            "name": "Middle East Tension",
            "direction": "LONG",
            "confidence": 100,
            "weight": 0.8
          },
          {
            "name": "Earnings Misses",
            "direction": "LONG",
            "confidence": 75,
            "weight": 0.4
          },
          {
            "name": "Trump Tariff Negative",
            "direction": "LONG",
            "confidence": 100,
            "weight": 0.5
          }
        ]
      },
      "price_context": {
        "ma20": 5082.51497,
        "ma50": 4841.77598,
        "ma200": 4352.05038,
        "w52_high": 5586.2002,
        "w52_low": 3590.0,
        "atr": 100.47147
      },
      "notes": "Safe haven. Strong in risk-off, tariff, and war scenarios.",
      "status": "ok",
      "hours_old": 0.0,
      "stale": false,
      "freshness": "\ud83d\udfe2 Fresh (0.0h)"
    }
  },
  "active_calls": [
    {
      "pair": "XAU/USD (Gold)",
      "symbol": "GC=F",
      "price": 5161.3,
      "day_chg_pct": 1.895,
      "direction": "LONG",
      "conviction": 76,
      "quality": "\ud83d\udd25 STRONG",
      "alignment": "ALIGNED \u2705",
      "entry": 5161.3,
      "target": 5412.47868,
      "stop": 5010.5928,
      "rr_ratio": 1.67,
      "key_driver": "Price above MA50 > MA200 (uptrend)",
      "hold_period": "3-7 days",
      "tech": {
        "direction": "LONG",
        "conviction": 60,
        "rsi": 56.4,
        "trend": "UPTREND",
        "perf_20d": 6.169,
        "reasons": [
          "Price above MA50 > MA200 (uptrend)",
          "Strong 20d momentum: +6.169%",
          "RSI healthy: 56.4"
        ]
      },
      "macro": {
        "direction": "LONG",
        "conviction": 90,
        "signals": [
          {
            "name": "Middle East Tension",
            "direction": "LONG",
            "confidence": 100,
            "weight": 0.8
          },
          {
            "name": "Earnings Misses",
            "direction": "LONG",
            "confidence": 75,
            "weight": 0.4
          },
          {
            "name": "Trump Tariff Negative",
            "direction": "LONG",
            "confidence": 100,
            "weight": 0.5
          }
        ]
      },
      "price_context": {
        "ma20": 5082.51497,
        "ma50": 4841.77598,
        "ma200": 4352.05038,
        "w52_high": 5586.2002,
        "w52_low": 3590.0,
        "atr": 100.47147
      },
      "notes": "Safe haven. Strong in risk-off, tariff, and war scenarios.",
      "status": "ok",
      "hours_old": 0.0,
      "stale": false,
      "freshness": "\ud83d\udfe2 Fresh (0.0h)"
    }
  ],
  "total_signals": 1,
  "top_call": {
    "pair": "XAU/USD (Gold)",
    "symbol": "GC=F",
    "price": 5161.3,
    "day_chg_pct": 1.895,
    "direction": "LONG",
    "conviction": 76,
    "quality": "\ud83d\udd25 STRONG",
    "alignment": "ALIGNED \u2705",
    "entry": 5161.3,
    "target": 5412.47868,
    "stop": 5010.5928,
    "rr_ratio": 1.67,
    "key_driver": "Price above MA50 > MA200 (uptrend)",
    "hold_period": "3-7 days",
    "tech": {
      "direction": "LONG",
      "conviction": 60,
      "rsi": 56.4,
      "trend": "UPTREND",
      "perf_20d": 6.169,
      "reasons": [
        "Price above MA50 > MA200 (uptrend)",
        "Strong 20d momentum: +6.169%",
        "RSI healthy: 56.4"
      ]
    },
    "macro": {
      "direction": "LONG",
      "conviction": 90,
      "signals": [
        {
          "name": "Middle East Tension",
          "direction": "LONG",
          "confidence": 100,
          "weight": 0.8
        },
        {
          "name": "Earnings Misses",
          "direction": "LONG",
          "confidence": 75,
          "weight": 0.4
        },
        {
          "name": "Trump Tariff Negative",
          "direction": "LONG",
          "confidence": 100,
          "weight": 0.5
        }
      ]
    },
    "price_context": {
      "ma20": 5082.51497,
      "ma50": 4841.77598,
      "ma200": 4352.05038,
      "w52_high": 5586.2002,
      "w52_low": 3590.0,
      "atr": 100.47147
    },
    "notes": "Safe haven. Strong in risk-off, tariff, and war scenarios.",
    "status": "ok",
    "hours_old": 0.0,
    "stale": false,
    "freshness": "\ud83d\udfe2 Fresh (0.0h)"
  }
}