{
  "total_resolved": 426,
  "wins": 138,
  "losses": 241,
  "flats": 47,
  "win_rate": 32.4,
  "avg_return": -0.97,
  "best_return": 9.92,
  "worst_return": -19.06,
  "by_score_tier": {
    "90-100": {
      "win_rate": 32.5,
      "count": 323,
      "avg_ret": -0.98
    },
    "75-89": {
      "win_rate": 17.5,
      "count": 57,
      "avg_ret": -2.33
    },
    "60-74": {
      "win_rate": 56.7,
      "count": 30,
      "avg_ret": 1.24
    },
    "below-60": {
      "win_rate": 33.3,
      "count": 15,
      "avg_ret": -0.14
    }
  },
  "by_category": {
    "SWING": {
      "win_rate": 12.5,
      "count": 32
    },
    "GROWTH CORE": {
      "win_rate": 31.8,
      "count": 22
    },
    "INCOME + GROWTH": {
      "win_rate": 51.4,
      "count": 37
    },
    "FHSA Conservative Growth": {
      "win_rate": 29.4,
      "count": 245
    },
    "DIVIDEND GROWTH": {
      "win_rate": 52.2,
      "count": 23
    },
    "WATCH": {
      "win_rate": 35.8,
      "count": 67
    }
  },
  "recent_10": [
    {
      "ticker": "TRP.TO",
      "date": "2026-03-23",
      "ret": 1.45,
      "outcome": "WIN",
      "score": 96
    },
    {
      "ticker": "TRP.TO",
      "date": "2026-03-24",
      "ret": -0.09,
      "outcome": "FLAT",
      "score": 96
    },
    {
      "ticker": "TRP.TO",
      "date": "2026-03-25",
      "ret": -0.09,
      "outcome": "FLAT",
      "score": 96
    },
    {
      "ticker": "ABBV",
      "date": "2026-03-26",
      "ret": 0.8,
      "outcome": "WIN",
      "score": 62
    },
    {
      "ticker": "ENB.TO",
      "date": "2026-03-27",
      "ret": -0.12,
      "outcome": "FLAT",
      "score": 96
    },
    {
      "ticker": "TD.TO",
      "date": "2026-03-27",
      "ret": 2.99,
      "outcome": "WIN",
      "score": 87
    },
    {
      "ticker": "ABBV",
      "date": "2026-03-27",
      "ret": -1.08,
      "outcome": "LOSS",
      "score": 51.400000000000006
    },
    {
      "ticker": "VZ",
      "date": "2026-03-27",
      "ret": -2.64,
      "outcome": "LOSS",
      "score": 96
    },
    {
      "ticker": "TRP.TO",
      "date": "2026-03-27",
      "ret": -0.34,
      "outcome": "LOSS",
      "score": 96
    },
    {
      "ticker": "CNQ.TO",
      "date": "2026-03-27",
      "ret": -4.77,
      "outcome": "LOSS",
      "score": 100
    }
  ],
  "streak": 1,
  "streak_type": "WIN",
  "time_weighted": {
    "tw_win_rate": 34.3,
    "tw_avg_return": -0.87,
    "tw_trend": "STABLE",
    "tw_30d_win_rate": 33.7,
    "tw_90d_win_rate": 32.4,
    "tw_30d_count": 406,
    "tw_90d_count": 426,
    "tw_lambda": 0.02,
    "tw_halflife_days": 35
  },
  "message": "32% win rate on 426 picks"
}